pytest_fixture_maker/__init__.py
pytest_fixture_maker/plugin.py
pytest_fixture_maker-0.2.0.dist-info/entry_points.txt
pytest_fixture_maker-0.2.0.dist-info/LICENSE
pytest_fixture_maker-0.2.0.dist-info/WHEEL
pytest_fixture_maker-0.2.0.dist-info/METADATA
pytest_fixture_maker-0.2.0.dist-info/RECORD
