Metadata-Version: 2.1
Name: pytest-fixture-maker
Version: 0.2.0
Summary: Pytest plugin to load fixtures from YAML files
Home-page: https://github.com/clayman083/pytest-fixture-maker
Keywords: pytest,fixtures
Author: Kirill Sumorokov
Author-email: sumorokov.k@gmail.com
Requires-Python: >=3.8,<4.0
Classifier: Framework :: Pytest
Classifier: License :: OSI Approved :: MIT License
Classifier: Operating System :: OS Independent
Classifier: Programming Language :: Python :: 3
Classifier: Programming Language :: Python :: 3.8
Classifier: Programming Language :: Python :: 3.9
Classifier: Topic :: Software Development :: Testing
Project-URL: Repository, https://github.com/clayman083/pytest-fixture-maker
